notifications/__init__.py
notifications/admin.py
notifications/middleware.py
notifications/translation.py
notifications/utils.py
notifications/api/__init__.py
notifications/api/filters.py
notifications/api/permissions.py
notifications/api/serializers.py
notifications/api/views.py
notifications/management/__init__.py
notifications/management/commands/__init__.py
notifications/management/commands/update_notification_cache.py
notifications/migrations/0001_initial.py
notifications/migrations/0002_add_image_field.py
notifications/migrations/0003_add_translations_and_url_filtering.py
notifications/migrations/0004_auto_20200915_1222.py
notifications/migrations/0005_auto_20220701_1341.py
notifications/migrations/0006_remove_all_sns_push_notification_setup.py
notifications/migrations/0007_auto_20230113_1417.py
notifications/migrations/__init__.py
notifications/models/__init__.py
notifications/models/notifications.py
notifications/models/push.py
notifications/push/__init__.py
notifications/push/fields.py
notifications/push/settings.py
notifications/static/notifications/css/notifications.css
notifications/static/notifications/font/notificationsfont.ttf
notifications/static/notifications/font/notificationsfont.woff
notifications/static/notifications/js/NotificationsOnlyAPI.js
notifications/templates/admin/notifications/notification/change_form.html
trackwell_notifications-4.1.4.dist-info/METADATA
trackwell_notifications-4.1.4.dist-info/WHEEL
trackwell_notifications-4.1.4.dist-info/top_level.txt
trackwell_notifications-4.1.4.dist-info/RECORD
