Metadata-Version: 2.1
Name: trackwell-notifications
Version: 4.1.4
Summary: A simple Django app to support Notifications.
Home-page: UNKNOWN
Author: trackwell
Author-email: 
License: NA
Platform: UNKNOWN
Classifier: Environment :: Web Environment
Classifier: Framework :: Django
Classifier: Framework :: Django :: 2.2
Classifier: Framework :: Django :: 3.2
Classifier: Intended Audience :: Developers
Classifier: Operating System :: OS Independent
Classifier: Programming Language :: Python
Classifier: Programming Language :: Python :: 3
Classifier: Topic :: Internet :: WWW/HTTP
Classifier: Topic :: Internet :: WWW/HTTP :: Dynamic Content
Requires-Dist: Django
Requires-Dist: djangorestframework
Requires-Dist: django-filter
Requires-Dist: django-modeltranslation
Requires-Dist: Pillow
Requires-Dist: firebase-admin (<6,>=5)
